<?xml version="1.0" encoding="utf-8"?>
<odoo>
    <data>
        <!-- Vistas PRESTAMO -->
        <record id="biblioteca_prestamo_list" model="ir.ui.view">
            <field name="name">biblioteca prestamo list</field>
            <field name="model">biblioteca.prestamo</field>
            <field name="arch" type="xml">
                <list>
                    <field name="usuario"/>
                    <field name="libro"/>
                    <field name="fecha_prestamo"/>
                    <field name="fecha_devolucion"/>
                    <field name="estado"/>
                    <field name="multa_bol"/>
                    <field name="multa"/>
                    <field name="fecha_max"/>
                    <field name="motivo_multa"/>
                </list>
            </field>
        </record>

        <record id="biblioteca_prestamo_form" model="ir.ui.view">
            <field name="name">biblioteca prestamo form</field>
            <field name="model">biblioteca.prestamo</field>
            <field name="arch" type="xml">
                <form>
                    <header>
                        <field name="estado" widget="statusbar"/>
                    </header>
                        <group colspan="2">
                    <group string="Datos de Préstamo">
                        <field name="usuario" options="{'no_create': true }"/>
                        <field name="libro" />
                        <field name="fecha_prestamo"/>
                        <field name="fecha_max" required="1"/>
                        <button string="Prestar" type="object" name="generar_prestamo"/>
                        <button string="Devolución" type="object" name="devolver_libro" class="btn-success"/>
                    </group>
                    <group string="Multa">
                        <field name="fecha_devolucion"/>
                        <field name="motivo_multa"/>
                        <field name="multa_bol"/>
                        <field name="multa"/>
                        <button string="Generar Multa" type="object" name="generar_multa" class="btn-danger"/>
                        </group>
                    </group>
                    <group>
                        <field name="personal" readonly="1"/>
                        <field name="name" readonly="1" nolabel="1"/>
                    </group>
                </form>
            </field>
        </record>

        <record model="ir.actions.act_window" id="biblioteca_prestamo_action_window">
            <field name="name">biblioteca prestamo</field>
            <field name="res_model">biblioteca.prestamo</field>
            <field name="view_mode">list,form</field>
        </record>

        <!-- Menú de Préstamo -->
        <menuitem name="Préstamos" id="biblioteca.prestamo" parent="biblioteca_menu" action="biblioteca_prestamo_action_window"/>
    </data>
</odoo>